{
  "__inputs": [],
  "__requires": [
    {
      "type": "panel",
      "id": "barchart",
      "name": "Bar chart",
      "version": ""
    },
    {
      "type": "panel",
      "id": "dalvany-image-panel",
      "name": "Dynamic image panel",
      "version": "2.3.0"
    },
    {
      "type": "grafana",
      "id": "grafana",
      "name": "Grafana",
      "version": "8.0.2"
    },
    {
      "type": "panel",
      "id": "stat",
      "name": "Stat",
      "version": ""
    },
    {
      "type": "panel",
      "id": "state-timeline",
      "name": "State timeline",
      "version": ""
    }
  ],
  "annotations": {
    "list": [
      {
        "builtIn": 1,
        "datasource": "-- Grafana --",
        "enable": true,
        "hide": true,
        "iconColor": "rgba(0, 211, 255, 1)",
        "name": "Annotations & Alerts",
        "type": "dashboard"
      }
    ]
  },
  "editable": true,
  "gnetId": null,
  "graphTooltip": 0,
  "id": null,
  "links": [],
  "panels": [
    {
      "datasource": null,
      "gridPos": {
        "h": 7,
        "w": 5,
        "x": 0,
        "y": 0
      },
      "id": 2,
      "options": {
        "alt_field": "",
        "baseUrl": "http://localhost:5000/image/",
        "height": "75",
        "icon_field": "",
        "overlay": {
          "bindings": {
            "bindings": [],
            "has_text": true,
            "unbounded": "#66666620"
          },
          "field": "",
          "height": {
            "size": 5,
            "unit": "%"
          },
          "position": "Top right",
          "width": {
            "size": 5,
            "unit": "%"
          }
        },
        "singleFill": true,
        "tooltip": false,
        "tooltip_date_elapsed": false,
        "tooltip_field": "",
        "tooltip_include_date": false,
        "tooltip_include_field": true,
        "underline": {
          "field": "",
          "text_size": "14"
        },
        "width": "75"
      },
      "targets": [
        {
          "refId": "A",
          "target": "LastMode",
          "type": "timeserie"
        }
      ],
      "title": "Dynamic Image ",
      "type": "dalvany-image-panel"
    },
    {
      "datasource": null,
      "fieldConfig": {
        "defaults": {
          "color": {
            "mode": "palette-classic"
          },
          "custom": {
            "axisLabel": "",
            "axisPlacement": "auto",
            "axisSoftMin": 0,
            "fillOpacity": 80,
            "gradientMode": "none",
            "hideFrom": {
              "legend": false,
              "tooltip": false,
              "viz": false
            },
            "lineWidth": 1
          },
          "mappings": [],
          "thresholds": {
            "mode": "absolute",
            "steps": [
              {
                "color": "green",
                "value": null
              },
              {
                "color": "red",
                "value": 80
              }
            ]
          }
        },
        "overrides": []
      },
      "gridPos": {
        "h": 15,
        "w": 12,
        "x": 5,
        "y": 0
      },
      "id": 7,
      "options": {
        "barWidth": 0.97,
        "groupWidth": 0.7,
        "legend": {
          "calcs": [],
          "displayMode": "list",
          "placement": "bottom"
        },
        "orientation": "auto",
        "showValue": "auto",
        "text": {},
        "tooltip": {
          "mode": "single"
        }
      },
      "pluginVersion": "8.0.2",
      "targets": [
        {
          "refId": "A",
          "target": "OkNokByRecipe",
          "type": "timeserie"
        }
      ],
      "title": "OK/NOK by Recipe",
      "type": "barchart"
    },
    {
      "datasource": null,
      "fieldConfig": {
        "defaults": {
          "color": {
            "mode": "thresholds"
          },
          "mappings": [],
          "thresholds": {
            "mode": "absolute",
            "steps": [
              {
                "color": "green",
                "value": null
              }
            ]
          }
        },
        "overrides": [
          {
            "matcher": {
              "id": "byName",
              "options": "Bad"
            },
            "properties": [
              {
                "id": "color",
                "value": {
                  "fixedColor": "light-orange",
                  "mode": "fixed"
                }
              }
            ]
          }
        ]
      },
      "gridPos": {
        "h": 15,
        "w": 7,
        "x": 17,
        "y": 0
      },
      "id": 9,
      "options": {
        "colorMode": "value",
        "graphMode": "area",
        "justifyMode": "auto",
        "orientation": "auto",
        "reduceOptions": {
          "calcs": [
            "lastNotNull"
          ],
          "fields": "",
          "values": true
        },
        "text": {},
        "textMode": "auto"
      },
      "pluginVersion": "8.0.2",
      "targets": [
        {
          "refId": "A",
          "target": "TotalOK",
          "type": "timeserie"
        }
      ],
      "title": "Good count",
      "type": "stat"
    },
    {
      "datasource": null,
      "fieldConfig": {
        "defaults": {
          "color": {
            "mode": "thresholds"
          },
          "mappings": [],
          "thresholds": {
            "mode": "absolute",
            "steps": [
              {
                "color": "text",
                "value": null
              }
            ]
          }
        },
        "overrides": []
      },
      "gridPos": {
        "h": 8,
        "w": 5,
        "x": 0,
        "y": 7
      },
      "id": 3,
      "options": {
        "colorMode": "value",
        "graphMode": "area",
        "justifyMode": "auto",
        "orientation": "auto",
        "reduceOptions": {
          "calcs": [
            "lastNotNull"
          ],
          "fields": "/^RecipeName$/",
          "values": true
        },
        "text": {},
        "textMode": "value"
      },
      "pluginVersion": "8.0.2",
      "targets": [
        {
          "refId": "A",
          "target": "LastMode",
          "type": "timeserie"
        }
      ],
      "title": "Recipe",
      "type": "stat"
    },
    {
      "datasource": null,
      "fieldConfig": {
        "defaults": {
          "color": {
            "mode": "thresholds"
          },
          "custom": {
            "fillOpacity": 70,
            "lineWidth": 0
          },
          "mappings": [
            {
              "options": {
                "Ground": {
                  "color": "text",
                  "index": 0
                },
                "Idle": {
                  "color": "super-light-purple",
                  "index": 2
                },
                "Service": {
                  "color": "light-red",
                  "index": 1
                }
              },
              "type": "value"
            }
          ],
          "thresholds": {
            "mode": "absolute",
            "steps": [
              {
                "color": "green",
                "value": null
              }
            ]
          }
        },
        "overrides": []
      },
      "gridPos": {
        "h": 7,
        "w": 24,
        "x": 0,
        "y": 15
      },
      "id": 5,
      "options": {
        "alignValue": "center",
        "legend": {
          "displayMode": "list",
          "placement": "bottom"
        },
        "mergeValues": true,
        "rowHeight": 0.9,
        "showValue": "auto",
        "tooltip": {
          "mode": "single"
        }
      },
      "targets": [
        {
          "refId": "A",
          "target": "StationModesTimeline",
          "type": "timeserie"
        }
      ],
      "title": "Station modes ",
      "type": "state-timeline"
    }
  ],
  "refresh": "",
  "schemaVersion": 30,
  "style": "dark",
  "tags": [],
  "templating": {
    "list": []
  },
  "time": {
    "from": "now-2d",
    "to": "now"
  },
  "timepicker": {},
  "timezone": "",
  "title": "TcOpen",
  "uid": "nug10Bank",
  "version": 8
}