<?xml version='1.0' encoding='UTF-8' ?>
<FileList>
  <File Reference="TcOpen.Inxton.TcoCore.Wpf.dll">
    <ToolboxItems
      VSCategory="TcOpen.Inxton.TcoCore.Wpf"
      BlendCategory="TcOpen.Inxton.TcoCore.Wpf"
    >
      <!--<Item Type="MaterialDesignThemes.Wpf.Badged" />-->
      <Item Type="Tco.Wpf.DynamicTreeView" />
      <Item Type="TcoCore.HealthIndicatorView" />
      <Item Type="TcoCore.TcoContextTreeView" />
      <Item Type="TcoCore.TcoDiagnosticsView" />
      <Item Type="TcoCore.TcoMomentaryTaskView" />
      <Item Type="TcoCore.TcoObjectTreeView" />
      <Item Type="TcoCore.TcoRemoteTaskServiceView" />
      <Item Type="TcoCore.TcoRemoteTaskView" />
      <Item Type="TcoCore.TcoSequencerModeControllerView" />
      <Item Type="TcoCore.TcoSequencerObserverView" />
      <Item Type="TcoCore.TcoSequencerBaseView" />
      <Item Type="TcoCore.TcoSignalInfoView" />
      <Item Type="TcoCore.TcoTaskView" />
      <Item Type="TcoCore.TcoTaskProgressBarView" />
      <Item Type="TcoCore.TcoToggleTaskView" />
    </ToolboxItems>
  </File>
</FileList>
